gptshell/GPTshell.py
gptshell/__init__.py
gptshell/lazycmd.py
lazy_commands-0.1.2.data/scripts/lazycmd.py
lazy_commands-0.1.2.dist-info/LICENSE
lazy_commands-0.1.2.dist-info/METADATA
lazy_commands-0.1.2.dist-info/WHEEL
lazy_commands-0.1.2.dist-info/top_level.txt
lazy_commands-0.1.2.dist-info/RECORD
